{"id": "typing", "path": "/home/willames/Documents/projetos-pessoais/pythonGames/helloWorld/.tox/mypy/lib/python3.10/site-packages/mypy/typeshed/stdlib/typing.pyi", "mtime": 1672880387, "size": 29318, "hash": "bfbec1520c827e9531e8f163177382dafda66c3107da5975f1db8b8fed9a16de", "data_mtime": 1672759465, "dependencies": ["_typeshed", "collections", "sys", "_collections_abc", "abc", "contextlib", "re", "types", "typing_extensions", "builtins", "array", "ctypes", "mmap", "pickle"], "suppressed": [], "options": {"warn_no_return": true, "strict_equality": true, "disallow_subclassing_any": false, "disable_bytearray_promotion": false, "allow_untyped_globals": false, "strict_optional": true, "always_true": [], "follow_imports_for_stubs": false, "implicit_reexport": false, "mypyc": false, "plugins": [], "disallow_any_decorated": false, "follow_imports": "normal", "enabled_error_codes": [], "enable_error_code": [], "bazel": false, "disallow_untyped_decorators": false, "platform": "linux", "disallow_untyped_defs": false, "disallow_any_explicit": false, "disable_error_code": [], "ignore_errors": false, "ignore_missing_imports": true, "disable_memoryview_promotion": false, "warn_unreachable": true, "disallow_any_expr": false, "check_untyped_defs": true, "disabled_error_codes": [], "allow_redefinition": false, "always_false": [], "disallow_untyped_calls": false, "implicit_optional": false, "strict_concatenate": false, "disallow_incomplete_defs": false, "disallow_any_generics": true, "warn_unused_ignores": false, "warn_return_any": true, "disallow_any_unimported": false, "local_partial_types": false}, "dep_prios": [5, 10, 10, 5, 5, 5, 5, 5, 5, 5, 30, 30, 30, 30], "dep_lines": [1, 2, 3, 4, 6, 7, 8, 9, 21, 1, 1, 1, 1, 1], "interface_hash": "2dd7a1c5e5c7dff0659922279152e82b5ca3b8eefe159ee5a85bd1b3faa433ee", "version_id": "0.991", "ignore_all": true, "plugin_data": null}